score.webassets-0.3.26-py3.7-nspkg.pth
score/webassets/__init__.py
score/webassets/_init.py
score/webassets/cli.py
score/webassets/proxy.py
score.webassets-0.3.26.dist-info/COPYING.LESSER.txt
score.webassets-0.3.26.dist-info/METADATA
score.webassets-0.3.26.dist-info/WHEEL
score.webassets-0.3.26.dist-info/entry_points.txt
score.webassets-0.3.26.dist-info/namespace_packages.txt
score.webassets-0.3.26.dist-info/top_level.txt
score.webassets-0.3.26.dist-info/RECORD
